nofus/__init__.py
nofus/configfile.py
nofus/logger.py
nofus-0.1.5.dist-info/LICENSE
nofus-0.1.5.dist-info/METADATA
nofus-0.1.5.dist-info/WHEEL
nofus-0.1.5.dist-info/top_level.txt
nofus-0.1.5.dist-info/RECORD
