Metadata-Version: 2.1
Name: nofus
Version: 0.1.5
Summary: NOFUS - Nate's One-File Utilities Stash
Home-page: https://github.com/natecollins/nofus-python/
Author: Nate Collins
Author-email: npcollins@gmail.com
License: BSD 2-clause
Platform: UNKNOWN
Classifier: Intended Audience :: Developers
Classifier: Development Status :: 3 - Alpha
Classifier: License :: OSI Approved :: BSD License
Classifier: Operating System :: OS Independent
Classifier: Programming Language :: Python
Classifier: Programming Language :: Python :: 3
